LICENSE
MANIFEST.in
README.rst
setup.py
django_gzipping_cache/__init__.py
django_gzipping_cache/__init__.pyc
django_gzipping_cache/cache.py
django_gzipping_cache/cache.pyc
django_gzipping_cache.egg-info/PKG-INFO
django_gzipping_cache.egg-info/SOURCES.txt
django_gzipping_cache.egg-info/dependency_links.txt
django_gzipping_cache.egg-info/not-zip-safe
django_gzipping_cache.egg-info/requires.txt
django_gzipping_cache.egg-info/top_level.txt
django_gzipping_cache/tests/__init__.py
django_gzipping_cache/tests/__init__.pyc
django_gzipping_cache/tests/test_django_gzipping_cache.py
django_gzipping_cache/tests/test_django_gzipping_cache.pyc