Metadata-Version: 1.1
Name: django-gzipping-cache
Version: 0.1.0
Summary: A wrapper for django caches that gzips cached values
Home-page: https://github.com/mapmyfitness/django-gzipping-cache
Author: MapMyFitness
Author-email: coreteam@mapmyfitnessinc.com
License: BSD
Download-URL: https://pypi.python.org/pypi/django-gzipping-cache
Platform: UNKNOWN
Classifier: Development Status :: 4 - Beta
Classifier: Environment :: Web Environment
Classifier: Framework :: Django
Classifier: Intended Audience :: Developers
Classifier: License :: OSI Approved :: BSD License
Classifier: Operating System :: OS Independent
Classifier: Programming Language :: Python
Classifier: Programming Language :: Python :: 2
Classifier: Programming Language :: Python :: 2.6
Classifier: Programming Language :: Python :: 2.7
Classifier: Topic :: Software Development :: Libraries :: Python Modules
